cg_atv2_python_insert/__init__.py
cg_atv2_python_insert/__main__.py
cg_atv2_python_insert/substitution.py
cg_atv2_python_insert-2024.1.16.1248.dist-info/METADATA
cg_atv2_python_insert-2024.1.16.1248.dist-info/WHEEL
cg_atv2_python_insert-2024.1.16.1248.dist-info/entry_points.txt
cg_atv2_python_insert-2024.1.16.1248.dist-info/RECORD
