Metadata-Version: 2.1
Name: cg-atv2-python-insert
Version: 2024.1.16.1248
Summary: 
License: MIT
Author: CodeGrade
Author-email: info@codegrade.com
Requires-Python: >=3.10,<4.0
Classifier: License :: OSI Approved :: MIT License
Classifier: Programming Language :: Python :: 3
Classifier: Programming Language :: Python :: 3.10
Classifier: Programming Language :: Python :: 3.11
Classifier: Programming Language :: Python :: 3.12
Requires-Dist: libcst (>=1.1.0,<2.0.0)
